captchium/__init__.py
captchium/captchium.py
captchium-1.1.5.dist-info/LICENSE
captchium-1.1.5.dist-info/METADATA
captchium-1.1.5.dist-info/WHEEL
captchium-1.1.5.dist-info/top_level.txt
captchium-1.1.5.dist-info/RECORD
