Metadata-Version: 2.1
Name: captchium
Version: 1.1.5
Summary: Python library for solving Google reCAPTCHA challenges
Home-page: https://github.com/d3kxrma/captchium
Author: dekxrma
Author-email: qqdjnuxez@gmail.com
License: MIT
Project-URL: Source, https://github.com/d3kxrma/captchium
Keywords: python,recaptcha,captcha,solver,selenium
Classifier: Development Status :: 5 - Production/Stable
Classifier: Intended Audience :: Developers
Classifier: Operating System :: Microsoft :: Windows :: Windows 10
Classifier: License :: OSI Approved :: MIT License
Classifier: Programming Language :: Python :: 3
License-File: LICENSE
Requires-Dist: requests
Requires-Dist: SpeechRecognition
Requires-Dist: selenium
